{
	"name": "Microsoft Dynamics NAV Get Product Quantity",
	"schemaDef": {
	  "$schema": "http://json-schema.org/draft-06/schema#",
	  "title": "Microsoft Dynamics NAV Get Product Quantity",
	  "type": "object",
	  "properties": {
	    "Item": {
	      "$ref": "#/definitions/Item"
	    }
	  },
	  "required": [
	    "Item"
	  ],
	  "additionalProperties": false,
	  "definitions": {
	    "Item": {
	      "$id": "/properties/Item",
	      "type": "object",
	      "properties": {
	        "Key": {
	          "$id": "/properties/Item/properties/Key",
	          "type": "string"
	        },
	        "No": {
	          "$id": "/properties/Item/properties/No",
	          "type": "string"
	        },
	        "Description": {
	          "$id": "/properties/Item/properties/Description",
	          "type": "string"
	        },
	        "Base_Unit_of_Measure": {
	          "$id": "/properties/Item/properties/Base_Unit_of_Measure",
	          "type": "string"
	        },
	        "Assembly_BOM": {
	          "$id": "/properties/Item/properties/Assembly_BOM",
	          "type": "boolean"
	        },
					"Shelf_No": {
						"$id": "/properties/Item/properties/Shelf_No",
						"type": "string"
					},
	        "Automatic_Ext_Texts": {
	          "$id": "/properties/Item/properties/Automatic_Ext_Texts",
	          "type": "boolean"
	        },
	        "Created_From_Nonstock_Item": {
	          "$id": "/properties/Item/properties/Created_From_Nonstock_Item",
	          "type": "boolean"
	        },
	        "Item_Category_Code": {
	          "$id": "/properties/Item/properties/Item_Category_Code",
	          "type": "string"
	        },
	        "Product_Group_Code": {
	          "$id": "/properties/Item/properties/Product_Group_Code",
	          "type": "string"
	        },
	        "Service_Item_Group": {
	          "$id": "/properties/Item/properties/Service_Item_Group",
	          "type": "string"
	        },
	        "Search_Description": {
	          "$id": "/properties/Item/properties/Search_Description",
	          "type": "string"
	        },
	        "Inventory": {
	          "$id": "/properties/Item/properties/Inventory",
	          "type": "number"
	        },
	        "Qty_on_Purch_Order": {
	          "$id": "/properties/Item/properties/Qty_on_Purch_Order",
	          "type": "number"
	        },
	        "Qty_on_Prod_Order": {
	          "$id": "/properties/Item/properties/Qty_on_Prod_Order",
	          "type": "number"
	        },
	        "Qty_on_Component_Lines": {
	          "$id": "/properties/Item/properties/Qty_on_Component_Lines",
	          "type": "number"
	        },
	        "Qty_on_Sales_Order": {
	          "$id": "/properties/Item/properties/Qty_on_Sales_Order",
	          "type": "number"
	        },
	        "Qty_on_Service_Order": {
	          "$id": "/properties/Item/properties/Qty_on_Service_Order",
	          "type": "number"
	        },
	        "Qty_on_Job_Order": {
	          "$id": "/properties/Item/properties/Qty_on_Job_Order",
	          "type": "number"
	        },
	        "Qty_on_Assembly_Order": {
	          "$id": "/properties/Item/properties/Qty_on_Assembly_Order",
	          "type": "number"
	        },
	        "Qty_on_Asm_Component": {
	          "$id": "/properties/Item/properties/Qty_on_Asm_Component",
	          "type": "number"
	        },
	        "Blocked": {
	          "$id": "/properties/Item/properties/Blocked",
	          "type": "boolean"
	        },
	        "Last_Date_Modified": {
	          "$id": "/properties/Item/properties/Last_Date_Modified",
	          "type": "string"
	        },
	        "StockoutWarningDefaultYes": {
	          "$id": "/properties/Item/properties/StockoutWarningDefaultYes",
	          "type": "string"
	        },
	        "PreventNegInventoryDefaultYes": {
	          "$id": "/properties/Item/properties/PreventNegInventoryDefaultYes",
	          "type": "string"
	        },
	        "Costing_Method": {
	          "$id": "/properties/Item/properties/Costing_Method",
	          "type": "string"
	        },
	        "Cost_is_Adjusted": {
	          "$id": "/properties/Item/properties/Cost_is_Adjusted",
	          "type": "boolean"
	        },
	        "Cost_is_Posted_to_G_L": {
	          "$id": "/properties/Item/properties/Cost_is_Posted_to_G_L",
	          "type": "boolean"
	        },
	        "Standard_Cost": {
	          "$id": "/properties/Item/properties/Standard_Cost",
	          "type": "number"
	        },
	        "Unit_Cost": {
	          "$id": "/properties/Item/properties/Unit_Cost",
	          "type": "number"
	        },
	        "Overhead_Rate": {
	          "$id": "/properties/Item/properties/Overhead_Rate",
	          "type": "number"
	        },
	        "Indirect_Cost_Percent": {
	          "$id": "/properties/Item/properties/Indirect_Cost_Percent",
	          "type": "number"
	        },
	        "Last_Direct_Cost": {
	          "$id": "/properties/Item/properties/Last_Direct_Cost",
	          "type": "number"
	        },
	        "Price_Profit_Calculation": {
	          "$id": "/properties/Item/properties/Price_Profit_Calculation",
	          "type": "string"
	        },
	        "Profit_Percent": {
	          "$id": "/properties/Item/properties/Profit_Percent",
	          "type": "number"
	        },
	        "Unit_Price": {
	          "$id": "/properties/Item/properties/Unit_Price",
	          "type": "number"
	        },
	        "Gen_Prod_Posting_Group": {
	          "$id": "/properties/Item/properties/Gen_Prod_Posting_Group",
	          "type": "string"
	        },
					"VAT_Prod_Posting_Group": {
						"$id": "/properties/Item/properties/VAT_Prod_Posting_Group",
						"type": "string"
					},
	        "Inventory_Posting_Group": {
	          "$id": "/properties/Item/properties/Inventory_Posting_Group",
	          "type": "string"
	        },
	        "Net_Invoiced_Qty": {
	          "$id": "/properties/Item/properties/Net_Invoiced_Qty",
	          "type": "number"
	        },
	        "Allow_Invoice_Disc": {
	          "$id": "/properties/Item/properties/Allow_Invoice_Disc",
	          "type": "boolean"
	        },
					"Item_Disc_Group": {
						"$id": "/properties/Item/properties/Item_Disc_Group",
						"type": "string"
					},
	        "Sales_Unit_of_Measure": {
	          "$id": "/properties/Item/properties/Sales_Unit_of_Measure",
	          "type": "string"
	        },
					"Application_Wksh_User_ID": {
						"$id": "/properties/Item/properties/Application_Wksh_User_ID",
						"type": "string"
					},
					"Tax_Group_Code": {
						"$id": "/properties/Item/properties/Tax_Group_Code",
						"type": "string"
					},
	        "Replenishment_System": {
	          "$id": "/properties/Item/properties/Replenishment_System",
	          "type": "string"
	        },
					"Lead_Time_Calculation": {
						"$id": "/properties/Item/properties/Lead_Time_Calculation",
						"type": "string"
					},
	        "Vendor_No": {
	          "$id": "/properties/Item/properties/Vendor_No",
	          "type": "string"
	        },
	        "Vendor_Item_No": {
	          "$id": "/properties/Item/properties/Vendor_Item_No",
	          "type": "string"
	        },
	        "Purch_Unit_of_Measure": {
	          "$id": "/properties/Item/properties/Purch_Unit_of_Measure",
	          "type": "string"
	        },
	        "Manufacturing_Policy": {
	          "$id": "/properties/Item/properties/Manufacturing_Policy",
	          "type": "string"
	        },
					"Routing_No": {
						"$id": "/properties/Item/properties/Routing_No",
						"type": "string"
					},
					"Production_BOM_No": {
						"$id": "/properties/Item/properties/Production_BOM_No",
						"type": "string"
					},
	        "Rounding_Precision": {
	          "$id": "/properties/Item/properties/Rounding_Precision",
	          "type": "number"
	        },
	        "Flushing_Method": {
	          "$id": "/properties/Item/properties/Flushing_Method",
	          "type": "string"
	        },
	        "Scrap_Percent": {
	          "$id": "/properties/Item/properties/Scrap_Percent",
	          "type": "number"
	        },
	        "Lot_Size": {
	          "$id": "/properties/Item/properties/Lot_Size",
	          "type": "number"
	        },
	        "Assembly_Policy": {
	          "$id": "/properties/Item/properties/Assembly_Policy",
	          "type": "string"
	        },
	        "Reordering_Policy": {
	          "$id": "/properties/Item/properties/Reordering_Policy",
	          "type": "string"
	        },
	        "Reserve": {
	          "$id": "/properties/Item/properties/Reserve",
	          "type": "string"
	        },
	        "Order_Tracking_Policy": {
	          "$id": "/properties/Item/properties/Order_Tracking_Policy",
	          "type": "string"
	        },
	        "Stockkeeping_Unit_Exists": {
	          "$id": "/properties/Item/properties/Stockkeeping_Unit_Exists",
	          "type": "boolean"
	        },
					"Dampener_Period": {
						"$id": "/properties/Item/properties/Dampener_Period",
						"type": "string"
					},
	        "Dampener_Quantity": {
	          "$id": "/properties/Item/properties/Dampener_Quantity",
	          "type": "number"
	        },
	        "Critical": {
	          "$id": "/properties/Item/properties/Critical",
	          "type": "boolean"
	        },
					"Safety_Lead_Time": {
						"$id": "/properties/Item/properties/Safety_Lead_Time",
						"type": "string"
					},
	        "Safety_Stock_Quantity": {
	          "$id": "/properties/Item/properties/Safety_Stock_Quantity",
	          "type": "number"
	        },
	        "Include_Inventory": {
	          "$id": "/properties/Item/properties/Include_Inventory",
	          "type": "boolean"
	        },
					"Lot_Accumulation_Period": {
						"$id": "/properties/Item/properties/Lot_Accumulation_Period",
						"type": "string"
					},
					"Rescheduling_Period": {
						"$id": "/properties/Item/properties/Rescheduling_Period",
						"type": "string"
					},
	        "Reorder_Point": {
	          "$id": "/properties/Item/properties/Reorder_Point",
	          "type": "number"
	        },
	        "Reorder_Quantity": {
	          "$id": "/properties/Item/properties/Reorder_Quantity",
	          "type": "number"
	        },
	        "Maximum_Inventory": {
	          "$id": "/properties/Item/properties/Maximum_Inventory",
	          "type": "number"
	        },
	        "Overflow_Level": {
	          "$id": "/properties/Item/properties/Overflow_Level",
	          "type": "number"
	        },
					"Time_Bucket": {
						"$id": "/properties/Item/properties/Time_Bucket",
						"type": "string"
					},
	        "Minimum_Order_Quantity": {
	          "$id": "/properties/Item/properties/Minimum_Order_Quantity",
	          "type": "number"
	        },
	        "Maximum_Order_Quantity": {
	          "$id": "/properties/Item/properties/Maximum_Order_Quantity",
	          "type": "number"
	        },
	        "Order_Multiple": {
	          "$id": "/properties/Item/properties/Order_Multiple",
	          "type": "number"
	        },
					"Tariff_No": {
	          "$id": "/properties/Item/properties/Tariff_No",
	          "type": "string"
	        },
					"Country_Region_of_Origin_Code": {
	          "$id": "/properties/Item/properties/Country_Region_of_Origin_Code",
	          "type": "string"
	        },
	        "Net_Weight": {
	          "$id": "/properties/Item/properties/Net_Weight",
	          "type": "number"
	        },
	        "Gross_Weight": {
	          "$id": "/properties/Item/properties/Gross_Weight",
	          "type": "number"
	        },
					"Item_Tracking_Code": {
						"$id": "/properties/Item/properties/Item_Tracking_Code",
						"type": "string"
					},
					"Serial_Nos": {
						"$id": "/properties/Item/properties/Serial_Nos",
						"type": "string"
					},
					"Lot_Nos": {
						"$id": "/properties/Item/properties/Lot_Nos",
						"type": "string"
					},
					"Expiration_Calculation": {
						"$id": "/properties/Item/properties/Expiration_Calculation",
						"type": "string"
					},
					"Special_Equipment_Code": {
						"$id": "/properties/Item/properties/Special_Equipment_Code",
						"type": "string"
					},
					"Put_away_Template_Code": {
						"$id": "/properties/Item/properties/Put_away_Template_Code",
						"type": "string"
					},
					"Put_away_Unit_of_Measure_Code": {
						"$id": "/properties/Item/properties/Put_away_Unit_of_Measure_Code",
						"type": "string"
					},
					"Phys_Invt_Counting_Period_Code": {
						"$id": "/properties/Item/properties/Phys_Invt_Counting_Period_Code",
						"type": "string"
					},
	        "Last_Phys_Invt_Date": {
	          "$id": "/properties/Item/properties/Last_Phys_Invt_Date",
	          "type": "string"
	        },
	        "Last_Counting_Period_Update": {
	          "$id": "/properties/Item/properties/Last_Counting_Period_Update",
	          "type": "string"
	        },
					"Next_Counting_Period": {
						"$id": "/properties/Item/properties/Next_Counting_Period",
						"type": "string"
					},
					"Identifier_Code": {
						"$id": "/properties/Item/properties/Identifier_Code",
						"type": "string"
					},
	        "Use_Cross_Docking": {
	          "$id": "/properties/Item/properties/Use_Cross_Docking",
	          "type": "boolean"
	        },
	        "Variant_Inventory": {
	          "$id": "/properties/Variant_Inventory",
            "type": "object",
						"properties": {
							"Key": {
								"$id": "/properties/Variant_Inventory/properties/Key",
								"type": "string"
							},
							"Code": {
								"$id": "/properties/Variant_Inventory/properties/Code",
								"type": "string"
							},
							"Description": {
								"$id": "/properties/Variant_Inventory/properties/Description",
								"type": "string"
							},
							"GrossRequirement": {
								"$id": "/properties/Variant_Inventory/properties/GrossRequirement",
								"type": "number"
							},
							"ScheduledRcpt": {
								"$id": "/properties/Variant_Inventory/properties/ScheduledRcpt",
								"type": "number"
							},
							"PlannedOrderRcpt": {
								"$id": "/properties/Variant_Inventory/properties/PlannedOrderRcpt",
								"type": "number"
							},
							"ProjAvailableBalance": {
								"$id": "/properties/Variant_Inventory/properties/ProjAvailableBalance",
								"type": "number"
							},
							"Item_Inventory": {
								"$id": "/properties/Variant_Inventory/properties/Item_Inventory",
								"type": "number"
							},
							"Item_Qty_on_Purch_Order": {
								"$id": "/properties/Variant_Inventory/properties/Item_Qty_on_Purch_Order",
								"type": "number"
							},
							"Item_Qty_on_Sales_Order": {
								"$id": "/properties/Variant_Inventory/properties/Item_Qty_on_Sales_Order",
								"type": "number"
							},
							"Item_Qty_on_Service_Order": {
								"$id": "/properties/Variant_Inventory/properties/Item_Qty_on_Service_Order",
								"type": "number"
							},
							"Item_Qty_on_Job_Order": {
								"$id": "/properties/Variant_Inventory/properties/Item_Qty_on_Job_Order",
								"type": "number"
							},
							"Item_Trans_Ord_Shipment_Qty": {
								"$id": "/properties/Variant_Inventory/properties/Item_Trans_Ord_Shipment_Qty",
								"type": "number"
							},
							"Item_Qty_on_Asm_Component": {
								"$id": "/properties/Variant_Inventory/properties/Item_Qty_on_Asm_Component",
								"type": "number"
							},
							"Item_Qty_on_Assembly_Order": {
								"$id": "/properties/Variant_Inventory/properties/Item_Qty_on_Assembly_Order",
								"type": "number"
							},
							"Item_Qty_in_Transit": {
								"$id": "/properties/Variant_Inventory/properties/Item_Qty_in_Transit",
								"type": "number"
							},
							"Item_Trans_Ord_Receipt_Qty": {
								"$id": "/properties/Variant_Inventory/properties/Item_Trans_Ord_Receipt_Qty",
								"type": "number"
							},
							"ExpectedInventory": {
								"$id": "/properties/Variant_Inventory/properties/ExpectedInventory",
								"type": "number"
							},
							"QtyAvailable": {
								"$id": "/properties/Variant_Inventory/properties/QtyAvailable",
								"type": "number"
							},
							"Item_Scheduled_Receipt_Qty": {
								"$id": "/properties/Variant_Inventory/properties/Item_Scheduled_Receipt_Qty",
								"type": "number"
							},
							"Item_Scheduled_Need_Qty": {
								"$id": "/properties/Variant_Inventory/properties/Item_Scheduled_Need_Qty",
								"type": "number"
							},
							"PlannedOrderReleases": {
								"$id": "/properties/Variant_Inventory/properties/PlannedOrderReleases",
								"type": "number"
							},
							"Item_Net_Change": {
								"$id": "/properties/Variant_Inventory/properties/Item_Net_Change",
								"type": "number"
							}
						}
	        }
	      }
	    }
	  }
	},
	"tags": [
		"Get",
		"Product",
		"Quantity"
	],
	"audit": {}
}
